{
  "city": "Algiers",
  "region": "Algeria",
  "tier": 4,
  "slug": "algiers",
  "annualVisitorsM": 1,
  "lastUpdated": "2026-06-24",
  "qualityThreshold": {
    "minViews": 5000,
    "publishedAfter": "2022-01-01T00:00:00Z"
  },
  "videoCount": 2,
  "videos": [
    {
      "videoId": "BmFTnGmORx4",
      "title": "Algiers Algeria: 13 BEST Things To Do In 2024 (Travel Guide)",
      "channel": "TravelScout",
      "publishedAt": "2024-06-20T08:56:26Z",
      "description": "Algiers, the capital of Algeria, is a city rich in history and culture, situated along the Mediterranean coast. Known for its white-washed buildings, earning it the nickname \"Algiers the White,\" the city features a blend of French colonial architecture and traditional Islamic structures. The historic Casbah, a UNESCO World Heritage site, with its narrow alleys and ancient palaces, offers a glimpse into the past. Modern Algiers boasts the impressive Martyrs' Memorial, vibrant markets, and bustling waterfronts. The city's diverse cultural scene includes museums, theaters, and music venues, making Algiers a captivating destination for history enthusiasts and travelers.\n\nContact us via email: ytmediabrands@gmail.com\n\n#travelscout",
      "tags": [
        "algeria",
        "algiers",
        "algiers algeria",
        "algeria algiers",
        "algiers city",
        "algeria travel",
        "algerian",
        "algeria 4k",
        "foreigners in algeria",
        "algeria vlog",
        "best things to do algiers",
        "foreigners in algiers",
        "algiers capital",
        "travel to algeria",
        "city guide algiers",
        "city guide algeria",
        "algeria algiers 4k",
        "algiers algeria 4k",
        "algiers 4k",
        "algerie",
        "travelling algeria",
        "travelling algiers",
        "to do algiers algeria",
        "algeria algiers city",
        "algiers city algeria"
      ],
      "viewCount": 18222,
      "likeCount": 480,
      "duration": "PT8M31S",
      "url": "https://www.youtube.com/watch?v=BmFTnGmORx4",
      "thumbnail": "https://i.ytimg.com/vi/BmFTnGmORx4/hqdefault.jpg",
      "transcriptLength": 8227,
      "transcript": "welcome to this complete algers Algeria guide where the Mediterranean Sea meets the Sahara Desert algers the vibrant capital of Algeria is a city of fascinating contrasts nestled between the Sea and the hills it's a place where the pulse of Modern Life intertwines with the Echoes of a rich and complex past the city's unique blend of French and Arab influences can be seen in its architecture Cuisine and culture a testament to its history as a Crossroads of civilizations from the narrow winding alleys of the ancient casbar to the wide boulevards of the French Colonial quarter algers is a city that invites exploration it's a place where every corner holds a story every Vista A Feast for the eyes with a wealth of historical sites vibrant markets and beautiful gardens alers offers a unique adventure for the Curious traveler with so much to explore let's dive into the top 13 things you can't miss in alers starting with the kasbar a UNESCO world heritage site that's a testament to alger's Rich past this ancient Citadel nestled within the heart of the city is a maze of winding Alleyways and traditional houses its architecture a blend of Ottoman and French influences paints a vivid picture of alger's diverse past the kazbar has been the backdrop of many historical events shaping the city's culture and identity visiting the kazbar is like stepping back in time a must visit for any history buff next up the notredam de a symbol of Rel religious Harmony in this predominantly Muslim country this stunning Cathedral perched on a cliff with panoramic views of alers was completed in the late 19th century its architecture a blend of Roman and Byzantine Styles is as captivating as its history inside and inscription reads Our Lady of Africa pray for us and for the Muslims this Cathedral is a testament to alger's cultural diversity offering a peaceful Retreat from the bustling City moving on to the ketawa mosque a jewel of moish architecture this fascinating structure nestled in the heart of alger's Casper has a rich history originally built in the 17th century it's a stunning blend of Ottoman and Andalusian Styles the mosque's intricate designs and Majestic minettes hold a special place in the hearts of the Muslim Community symbolizing their Dee rooted Faith this mosque is a beautiful representation of alger's Islamic history and culture and now the martyr's memorial an emblem of algeria's fight for independence this commanding Monument erected in the early '70s stands tall as a symbol of the nation's resilience it commemorates the hundreds of thousands who sacrificed their lives during the Algerian war three colossal Palm leaves intertwined Tower over the city their points reaching towards the heavens from here you can take in breathtaking panoramas of alers a city that owes its freedom to the martyrs represented by this Memorial this Monument is a poignant reminder of algeria's struggle for freedom and the people who gave their lives for it next the Bardo national museum of prehistory and ethnography a treasure Trove of Algerian history and culture nestled in an ottoman era Mansion this museum is an architectonic Marvel its vast collection showcases algeria's Journey from prehistoric times to the modern era preserving the nation's Heritage in a captivating display of artifacts fossils and traditional art from ancient Pottery to tribal costumes the Bardo museum is like a time capsule transporting visitors through algeria's rich and diverse history this Museum offers a fascinating insight into algeria's rich and diverse history uh moving on to the jardan de dama a green Oasis in the Heart of the City established in the mid 19th century it's a Botanical Wonder boasting over a thousand different plant species from towering Palms to delicate orchids amidst alger's Lively hum the garden offers a tranquil Retreat its Le paths Whispering stories of Botanical exploration here the city's clamor Fades into the rustling of leaves and the gentle song of birds this Garden is a perfect spot for nature lovers and those seeking Tranquility in the heart of algers next up the Museum of Modern Art of algers a hub for contemporary Algerian art this space is a vibrant canvas reflecting algeria's artistic pulse showcasing a diverse collection of visual art it's not just a museum it's an active participant in the art World organizing exhibitions and promoting local talent from sculptures to paintings from established artists to the upand coming mamama is a Living testament to the dynamism of Algerian art this museum is a must visit for art enthusiasts offering a window into algeria's vibrant art scene moving on to the place of the martyrs a historic Square in the Heart of the City this Grand Plaza has seen the passage of time its Stones bearing witness to alger's vibrant history its home to significant monuments each with a tale to tell over the years it has also become a social epicenter where locals gather to share stories sip on traditional mint tea or simply watch the world go by this square is a bustling Hub of activity offering a glimpse into the daily life of algers next the P De Ray a historic Palace complex that's a testament to alger's ottoman past this remarkable compound built in the late 16th century is a dazzling Showcase of Ottoman architecture imagine walking through the labyrinthine corridors each turn revealing intricate mosaics and ornate archways and let's not forget the stunning views it offers of the Mediterranean Sea it's as if the Azure waves are an extension of the palace itself this Palace is a beautiful reminder of aler Ottoman history offering stunning views of the sea and now the great Mosque of alers one of the oldest mosques in Africa this architectural Marvel's Roots Trace back to the 10th Century it's a testament to the stunning blend of berber and Andalusian Styles featuring intricate carvings and stunning mosaics the mosque is not just a place of worship but a Cornerstone of the Muslim Community hosting educational and social events its towering minet has witnessed centuries of History unfold this mosque is a beautiful representation of alger's Islamic history and culture next up the National Museum of Fine Arts of algers home to some of the finest art collections in Africa with a treasure Trove of over 8 thousand works of art it's a sanctuary for art lovers the museum showcases a variety of exhibitions each telling a unique story of Algerian art from ancient to contemporary pieces it serves as a custodian of algeria's artistic Heritage promoting the country's cultural identity this museum is a must visit for art enthusiasts offering a window into algeria's Rich art history moving on to the alger's Cornish a Scenic prominade along the Mediterranean Sea this vibrant stretch of is a feast For The Senses with panoramic sea views that could steal your breath away listen to the symphony of waves while sipping coffee from the bustling cafes or save a delicious local cuisine at the numerous restaurants dotted along the prominade it's a Social Hub brimming with life and laughter where the city comes to relax and enjoy the Mediterranean charm this prominade is a perfect spot for a leisurely stroll offering breathtaking views of the sea and finally the elazar Hotel a Historic Hotel that's a symbol of alger's colonial past once a Grand Mansion built in the 19th century it was transformed into a luxury hotel in the mid 20th century its unique architecture fuses French Colonial and traditional Algerian Styles creating a visual spectacle this hotel has hosted many a famed personality and has been a Silent Witness to alger's evolving history this hotel is a testament to alger's Colonial history offering a unique blend of French and Algerian influences and there you have it the top 13 things to do in algers from the historic kasbar and ketawa mosque the artfil mama and National Museum of Fine Arts the Lush jardan Desai du Hammer to the scenic alers Cornish each attraction a testament to alger's Rich history culture and natural beauty whether you're a history buff an art Enthusiast or a nature lover alers has something for everyone so pack your bags and get ready to explore this fascinating City",
      "knowledge": {
        "places": [
          "Algiers Algeria",
          "Things",
          "Travel Guide",
          "Algeria",
          "Mediterranean",
          "Known",
          "White",
          "French",
          "Islamic",
          "The",
          "Casbah",
          "World Heritage",
          "Modern Algiers",
          "Martyrs",
          "Memorial",
          "Contact",
          "Mediterranean Sea",
          "Sahara Desert",
          "Sea",
          "Modern Life",
          "Echoes",
          "Arab",
          "Cuisine",
          "Crossroads",
          "French Colonial",
          "Vista",
          "Feast",
          "Curious",
          "Rich",
          "Citadel",
          "Alleyways",
          "Ottoman",
          "Rel",
          "Harmony",
          "Muslim",
          "Cathedral",
          "Roman",
          "Byzantine Styles",
          "Our Lady",
          "Africa"
        ],
        "safetyNotes": [],
        "recommendations": [
          "Algiers Algeria: 13 BEST Things To Do In 2024 (Travel Guide)"
        ]
      }
    },
    {
      "videoId": "swi80oHnLzI",
      "title": "Algiers, Algeria - 20 Things to Do in 4 Days | Algeria - Algiers Travel Guide",
      "channel": "Top3Videos",
      "publishedAt": "2025-03-08T05:27:36Z",
      "description": "Algiers, Algeria - 20 Things to Do in 4 Days | Algeria - Algiers Travel Guide\n\nDiscover the magic of Algiers in this ultimate 4-day travel guide! From the historic Casbah to breathtaking Mediterranean views, we explore over 20 must-visit locations, including the iconic Martyrs’ Memorial, the stunning Notre-Dame d'Afrique, and the ancient Roman ruins of Tipaza. Indulge in authentic Algerian cuisine, from chakhchoukha to fresh seafood, and uncover hidden gems like the vibrant streets of Bab El Oued and the scenic Cap Caxine lighthouse. Whether you're drawn to the city's rich history, artistic heritage, or picturesque coastline, this journey offers something unforgettable.\n\nJoin us as we navigate Algiers’ vibrant culture, Ottoman and Moorish architecture, and fascinating museums like the Bardo and National Museum of Fine Arts. Experience the beauty of Jardin d’Essai, relax on the beaches of Palm Beach, and end your trip with a breathtaking view from Chenoua Mountain. Don’t miss out—like, subscribe, and stay tuned for more incredible travel adventures! \n\n✅ Don't forget to watch our recent videos.\n\n⏩ https://youtu.be/mM_q4vW8MoI\n⏩ https://youtu.be/Ga3eTAOuGug\n⏩ https://youtu.be/81IHiVSy2K8\n⏩ https://youtu.be/-R_Sclz8yW0\n⏩ https://youtu.be/aSqr5Lb74iU\n\n👉 Our Travel Gear\nhttps://top3videos.etsy.com\n\n👉 Subscribe to our channel. And press the bell🔔 icon. \nhttps://www.youtube.com/@Top3Videos/f... ⏰ Video Duration: 00:09:15\n\n👉 Don't forget to tell me about your opinion in the comments below. \n🙏 Thank you for supporting “Top3Videos” 🙏\n\n✅ You can follow us on the Social Media Links Below: ✿ STAY CONNECTED ✿ \n⏩ https://www.facebook.com/profile.php?... \n\nThanks for watching our video.",
      "tags": [
        "algeria travel",
        "algiers travel",
        "how to travel",
        "things to do in algeria",
        "algiers travel guide",
        "visit algiers",
        "things to do in algiers",
        "best places in algiers",
        "algiers tourism",
        "algiers algeria",
        "casbah of algiers",
        "algiers attractions",
        "travel to algeria",
        "algeria tourism",
        "top places in algiers",
        "algiers vlog",
        "algiers city tour",
        "best food in algiers",
        "where to go in algiers",
        "top 3 videos"
      ],
      "viewCount": 5732,
      "likeCount": 33,
      "duration": "PT9M15S",
      "url": "https://www.youtube.com/watch?v=swi80oHnLzI",
      "thumbnail": "https://i.ytimg.com/vi/swi80oHnLzI/hqdefault.jpg",
      "transcriptLength": 8092,
      "transcript": "welcome to algers the stunning capital of Algeria a city where history Rich culture and breathtaking Landscapes come together in Perfect Harmony over the next 4 days we'll explore more than 20 must visit locations indulge in authentic Algerian Cuisine and uncover a secret spot that will leave you in awe stay with us until the end because our final Discovery is something you won't want to miss are you ready let's begin day one we begin our journey in the soul of the city the kasba of algers this UNESCO world heritage site is a Labyrinth of narrow Alleyways hidden Courtyards and centuries old homes as we wander through the bustling streets we pass ancient palaces stunning mosques and Artisans crafting traditional Goods the scent of freshly baked bread fills the air drawing this deeper into the maze next we head to the National Museum of Arts and popular Traditions a cultural gem showcasing algeria's Rich Heritage located in a beautifully preserved ottoman Arab Palace in the cosba of alers the museum offers a deep dive into traditional Algerian craftsmanship arts and daily life a great Insight of the local traditions and a Hidden Gem for your adventure and at the foot of the kasba stands ketawa mosque a masterpiece of morish and ottoman architecture originally built in the 17th century this mosque has witnessed alger's turbulent history and remains a symbol of resilience just a short walk away we arrive at pet de Riz also known as Bastion 23 it served as a residence for high-ranking officials including the rise Naval commanders of the Algerian Corsair this beautifully preserved Fortress offers stunning sea views one of the few remaining parts of alger's old Waterfront and a glimp into the opulent lifestyle of the Ottoman rulers today it functions as a cultural and Exhibition Center after an exciting morning we stop at darl jazzer to try chak Chuka shredded flatbread soaked in a flavorful tomato and lamb sauce served with chickpeas and spices it's a must try dish in alers a glass of refreshing mint tea makes the perfect finish next we visit the iconic martyr Memorial a towering concrete structure honoring those who fought for algeria's independence from here we get one of the best panoramic views of the city nearby is the Army museum it showcases algeria's struggles and victories particularly focusing on the War of Independence against French colonial rule here you can see War Tanks aircrafts missiles uniforms and artifacts another Hidden Gem for your adventure as the afternoon light softens we enter jardan DSI or also called the botanic Garden Hammer it's a lush Botanical Garden that feels like an oasis in the city with towering palm trees exotic plants and Serene walkways it's the perfect place to unwind to end our first day we make our way to El madania Viewpoint where the Golden Glow of the Setting Sun bathes alers in an ethereal light day two begins with a visit to notron De fre a magnificent Basilica overlooking the sea this 19th century Church church with its stunning domes and intricate mosaics is a symbol of algeria's diverse Heritage we then explore the Lively neighborhood of bab El Ed where the true Spirit of algers Comes Alive a short drive takes us to rise hamdu Village named after the famous Algerian Corsair rise hamdu it's a Charming seaside village with a relaxed atmosphere traditional fishing port and Maritime Heritage it retains a local authentic charm with narrow streets and offers outstanding Scenic Mediterranean views for lunch we stop at Le doin a seafood restaurant renowned for its grilled sardines and fresh Mediterranean fish next we head to cap cine one of the tallest and most important lighthouses in Algeria guiding Maritime traffic near the Bay of alers the fresh Sea Breeze and endless ocean views make this a memorable stop no trip to alers is complete without a beach stop at PL Mori and Palm Beach we dip our toes in the turquoise Waters of the Mediterranean as the day winds down we enjoy a fine dining experience at Lantra where we Savor cuscus Royal fluffy semolina top with tender lamb merue sausage and a medley of vegetables day three starts with a deep dive into algeria's Rich Heritage of the National Museum of Fine Arts one of the largest art museums in Africa the museum houses an extensive collection of paintings sculpt and decorative Arts spanning various periods and styles and its diverse exhibitions make it a cultural treasure showcasing algeria's artistic Heritage and its connections to Global art movements or you can visit the Museum of Modern Arts housed in a beautifully restored colonial era building that was once the gallery's aluan a former department store it features temporary and permanent exhibitions highlighting Works in painting sculpture photography digital art and mixed media it serves as a cultural Hub hosting artistic events workshops and conferences fostering dialogue between Algerian and international artists it is a must visit for art lovers interested in algeria's Dynamic and evolving Contemporary Art scene next we explore the fascinating Bardo Museum showcasing algeria's prehistoric Heritage and diverse cultural Traditions housed in a beautiful 19th century morish Villa the museum itself is an architectural G gem featuring intricate tile work wooden ceilings and a peaceful garden its collection includes prehistoric artifacts such as ancient fossils Rock carvings and tools from algeria's early civilizations as well as ethnographic exhibits displaying traditional clothing jewelry musical instruments and Berber crafts the BAU Museum offers a deep dive into algeria's Rich history anthropology and cultural diversity a must visit place for lunch we try borc a crispy pastry filled with spiced meat and cheese served alongside a bowl of Herrera a rich and Hardy soup in the afternoon we step inside darhan patcha a grand 18th century mansion in a residence of Hanan patcha the day of alers this magnificent Palace served as a guest house for high-ranking officials and foreign diplomats including Napoleon theii the palace is known for its stunning moish architecture featuring intricate tile work carved wooden ceilings marble columns and elegant Courtyards as evening Falls we uncover a hidden rooftop Cafe in the casba Where We Sip strong Algerian Coffee while gazing at the illuminated Skyline and enjoying a night view of the great Mosque of algers day four on our final day we take a short trip to tipaza known for its stunning Mediterranean views and Rich historical Heritage it was originally a Phoenician Trading Post before becoming a major Ro Roman Colony today the site is famous for its UNESCO listed Roman ruins we start by exploring the well preserved archaeological Park which features remnant of Roman Punic early Christian and Byzantine civilizations making it an exceptional historical site and the Park's Scenic location overlooking the Mediterranean enhances its charm offering you a blend of history and breathtaking Coastal views truly mesmerizing don't miss the grand amphi theater a well-preserved Roman Arena used for entertainment next we visit the Royal melum of morania also known as Tombo de laan It is believed to be the tomb of King Juba II and Queen Cleopatra Seline II the daughter of Cleopatra iith and Mark Anthony this circular Stone structure standing over 30 m tall and 60 m in diameter resembles a steed pyramid and combines Egyptian Greek and Roman architectural uences despite its Grandeur the tomb has never been fully excavated adding to its mystery for lunch we indulge in delicious grilled lobster and fresh oysters while enjoying the ocean breeze for our grand finale we take a short hike up shinua Mountain the view from the top is breathtaking alers in the distance the Mediterranean stretching endlessly it's the perfect end to an unforgettable Journey from the historic kasba to Med Mediterranean beaches cultural landmarks to Hidden gems alers is a city like no other if this journey has inspired you don't forget to like subscribe and stay tuned for more incredible Adventures ma Sal Lama",
      "knowledge": {
        "places": [
          "Algeria",
          "Things",
          "Days",
          "Algiers Travel Guide",
          "Discover",
          "Casbah",
          "Mediterranean",
          "Martyrs",
          "Memorial",
          "Notre",
          "Dame",
          "Afrique",
          "Roman",
          "Tipaza",
          "Indulge",
          "Algerian",
          "Bab",
          "Oued",
          "Cap Caxine",
          "Whether",
          "Join",
          "Ottoman",
          "Moorish",
          "Bardo",
          "National Museum",
          "Fine Arts",
          "Experience",
          "Jardin",
          "Essai",
          "Palm Beach",
          "Chenoua Mountain",
          "Don",
          "Subscribe",
          "And",
          "Video Duration",
          "Thank",
          "You",
          "Social Media Links",
          "Below",
          "Rich"
        ],
        "safetyNotes": [
          "✅ Don't forget to watch our recent videos",
          "👉 Don't forget to tell me about your opinion in the comments below"
        ],
        "recommendations": [
          "Indulge in authentic Algerian cuisine, from chakhchoukha to fresh seafood, and uncover hidden gems like the vibrant streets of Bab El Oued and the scenic Cap Caxine lighthouse"
        ]
      }
    }
  ],
  "aggregated": {
    "topPlaces": [
      {
        "place": "Things",
        "count": 2
      },
      {
        "place": "Algeria",
        "count": 2
      },
      {
        "place": "Mediterranean",
        "count": 2
      },
      {
        "place": "Casbah",
        "count": 2
      },
      {
        "place": "Martyrs",
        "count": 2
      },
      {
        "place": "Memorial",
        "count": 2
      },
      {
        "place": "Rich",
        "count": 2
      },
      {
        "place": "Ottoman",
        "count": 2
      },
      {
        "place": "Roman",
        "count": 2
      },
      {
        "place": "Algiers Algeria",
        "count": 1
      },
      {
        "place": "Travel Guide",
        "count": 1
      },
      {
        "place": "Known",
        "count": 1
      },
      {
        "place": "White",
        "count": 1
      },
      {
        "place": "French",
        "count": 1
      },
      {
        "place": "Islamic",
        "count": 1
      },
      {
        "place": "The",
        "count": 1
      },
      {
        "place": "World Heritage",
        "count": 1
      },
      {
        "place": "Modern Algiers",
        "count": 1
      },
      {
        "place": "Contact",
        "count": 1
      },
      {
        "place": "Mediterranean Sea",
        "count": 1
      },
      {
        "place": "Sahara Desert",
        "count": 1
      },
      {
        "place": "Sea",
        "count": 1
      },
      {
        "place": "Modern Life",
        "count": 1
      },
      {
        "place": "Echoes",
        "count": 1
      },
      {
        "place": "Arab",
        "count": 1
      },
      {
        "place": "Cuisine",
        "count": 1
      },
      {
        "place": "Crossroads",
        "count": 1
      },
      {
        "place": "French Colonial",
        "count": 1
      },
      {
        "place": "Vista",
        "count": 1
      },
      {
        "place": "Feast",
        "count": 1
      }
    ],
    "safetyNotes": [
      "✅ Don't forget to watch our recent videos",
      "👉 Don't forget to tell me about your opinion in the comments below"
    ],
    "recommendations": [
      "Algiers Algeria: 13 BEST Things To Do In 2024 (Travel Guide)",
      "Indulge in authentic Algerian cuisine, from chakhchoukha to fresh seafood, and uncover hidden gems like the vibrant streets of Bab El Oued and the scenic Cap Caxine lighthouse"
    ]
  }
}